{
	"$schema": "https://biomejs.dev/schemas/2.1.1/schema.json",
	"assist": {
		"actions": {
			"source": {
				"organizeImports": "on"
			}
		},
		"enabled": true
	},
	"css": {
		"formatter": {
			"quoteStyle": "double"
		}
	},
	"files": {
		"ignoreUnknown": false,
		"includes": [
			"**",
			"!**/node_modules",
			"!tgui/public",
			"tgui/public/tgui.html",
			"!tgui/packages/tgui-setup/helpers.js",
			"!tgui/packages/tgui-bench"
		]
	},
	"formatter": {
		"enabled": true,
		"indentStyle": "tab",
		"lineEnding": "lf"
	},
	"javascript": {
		"formatter": {
			"indentStyle": "space",
			"quoteStyle": "single"
		}
	},
	"linter": {
		"enabled": true,
		"rules": {
			"recommended": true,
			"a11y": "off",
			"correctness": {
				"noUnusedImports": "warn",
				"noUnusedVariables": "off",
				"useExhaustiveDependencies": "off",
				"noUnusedFunctionParameters": "off"
			},
			"security": {
				"noDangerouslySetInnerHtml": "off"
			},
			"style": {
				"noNonNullAssertion": "off",
				"useTemplate": "off"
			},
			"suspicious": {
				"noArrayIndexKey": "off",
				"noExplicitAny": "off",
				"noImplicitAnyLet": "off"
			}
		}
	},
	"vcs": {
		"clientKind": "git",
		"enabled": false,
		"useIgnoreFile": false
	}
}
