{
	"dm_type": "/datum/ai_controller/basic_controller/bee",
	"type": "selector",
	"children": [
		{
			"type": "subtree",
			"subtype": "/datum/bt_node/subtree/fail",
			"override_id": "SUBPLAN_ID_PET_COMMAND"
		},
		{
			"type": "selector",
			"children": [
				{
					"type": "decorator",
					"decorator": "/datum/bt_node/decorator/bb_key_set",
					"config": {
						"key": "BB_CURRENT_HOME",
						"invert": true
					},
					"child": {
						"type": "leaf",
						"behavior": "/datum/bt_node/ai_behavior/find_hive",
						"args": []
					}
				},
				{
					"type": "sequence",
					"children": [
						{
							"type": "leaf",
							"behavior": "/datum/bt_node/ai_behavior/move_to_target",
							"args": ["BB_CURRENT_HOME", 1, false]
						},
						{
							"type": "leaf",
							"behavior": "/datum/bt_node/ai_behavior/inhabit_hive",
							"args": []
						}
					]
				}
			]
		},
		{
			"type": "leaf",
			"behavior": "/datum/bt_node/ai_behavior/enter_exit_hive",
			"args": []
		},
		{
			"type": "selector",
			"children": [
				{
					"type": "decorator",
					"decorator": "/datum/bt_node/decorator/bb_key_set",
					"config": {
						"key": "BB_TARGET_HYDRO",
						"observer_abort": "BT_ABORT_BOTH"
					},
					"child": {
						"type": "sequence",
						"children": [
							{
								"type": "leaf",
								"behavior": "/datum/bt_node/ai_behavior/move_to_target",
								"args": ["BB_TARGET_HYDRO", 1, false]
							},
							{
								"type": "leaf",
								"behavior": "/datum/bt_node/ai_behavior/pollinate_hydro",
								"args": []
							}
						]
					}
				},
				{
					"type": "leaf",
					"behavior": "/datum/bt_node/ai_behavior/find_pollination_target",
					"args": []
				}
			]
		},
		{
			"type": "subtree",
			"subtype": "/datum/bt_node/subtree/simple_hostile_combat"
		}
	]
}
